{
  "app": {
    "version": {
      "premium": "פּרֶמיָה",
      "free": "גרסה חינם"
    }
  },
  "presentation": [
    {
      "title": "תרגול לראיון העבודה הבא שלך!",
      "message": "האם נטילת ראיונות עבודה גורמים לך לחיצה וחרדה?\nאולי אתה עדיין מרגיש לא מוכן לקחת ראיונות עבודה?\nזו האפליקציה המושלמת לתרגל את כישורי השיחה שלך במסגרת ראיון עבודה!"
    },
    {
      "title": "היו מוכנים לתפקיד הבא שלכם!",
      "message": "Intelliviewer Job משתמש בכוח של בינה מלאכותית כדי לערוך ראיונות עבודה מדומים ריאליסטיים כדי לעזור לך לרתום את כישורי השיחה הדרושים בכדי לעשות רושם טוב על מגייסי החיים האמיתיים ולהפוך אותך למוכן לאס את הראיון הבא שלך בחיים האמיתיים."
    },
    {
      "title": "מנוי פרימיום:",
      "message": "קבל דוח בסוף כל ראיון המסכם את השיחה עם משוב ועצות כיצד לשפר את הסיכוי שלך להתקבל לעבודה בראיון עבודה אמיתי."
    }
  ],
  "navigation": {
    "page": {
      "home": "בַּיִת",
      "interview": "רֵאָיוֹן",
      "resume_cv": "קוֹרוֹת חַיִים",
      "history": "הִיסטוֹרִיָה",
      "history_entry": "כניסה להיסטוריה",
      "reports": "דוחות",
      "settings": "הגדרות"
    }
  },
  "title": {
    "attention": "תְשׁוּמַת לֵב",
    "information": "מֵידָע"
  },
  "label": {
    "search": "לְחַפֵּשׂ"
  },
  "button": {
    "ok": "בְּסֵדֶר",
    "back": "בְּחֲזָרָה",
    "close": "לִסְגוֹר",
    "cancel": "לְבַטֵל",
    "delete": "לִמְחוֹק",
    "review": "סְקִירָה",
    "subscribe": "הירשם"
  },
  "language": {
    "title": "שָׂפָה",
    "select": "בחר שפה",
    "altered": "השפה השתנתה"
  },
  "history": {
    "empty": "היסטוריה ריקה",
    "delete": {
      "list": {
        "title": "למחוק את ההיסטוריה?",
        "message": "האם אתה בטוח שאתה רוצה למחוק את כל ההיסטוריה?",
        "deleted": "ההיסטוריה נמחקה."
      },
      "entry": {
        "title": "למחוק ראיון?",
        "message": "האם אתה בטוח שאתה רוצה למחוק את הראיון הזה?",
        "deleted": "ההיסטוריה נמחקה."
      }
    }
  },
  "resume": {
    "fields": {
      "name": "שֵׁם",
      "first_name": "שֵׁם פְּרַטִי",
      "date_of_birth": "תַאֲרִיך לֵידָה",
      "job_position": "תפקיד עבודה",
      "job_position_detailed": "תפקיד תפקיד מפורט",
      "education": "הַשׂכָּלָה",
      "courses": "קורסים",
      "experience": "הִתנַסוּת",
      "add": {
        "education": "הוסף חינוך חדש",
        "courses": "הוסף קורס חדש",
        "experience": "הוסף חוויה חדשה"
      },
      "error": {
        "validation": {
          "title": "שגיאת אימות",
          "invalid_fields": "הכנס תפקיד תפקיד תפקיד תקף להגיש מועמדות לראיון עבודה חדש.\nלְחִלוּפִין",
          "unable_to_validate": "לא ניתן לאמת שדות."
        }
      }
    },
    "education": {
      "institution": "מוֹסָד",
      "degree": "תוֹאַר",
      "start": "הַתחָלָה",
      "end": "סוֹף"
    },
    "courses": {
      "institution": "מוֹסָד",
      "title_of_course": "כותרת כמובן",
      "course_load": "עומס קורס"
    },
    "experience": {
      "company": "חֶברָה",
      "position": "מַצָב",
      "start": "הַתחָלָה",
      "end": "סוֹף"
    }
  },
  "settings": {
    "color_scheme": {
      "name": "נושא אפל",
      "description": "בחר בין נושא אור כהה.\nמוגדר אוטומטית לעיצוב המכשיר בפעם הראשונה שתפתח את האפליקציה."
    },
    "language": {
      "name": "שָׂפָה",
      "description": "בחר את השפה המועדפת שתציג בעת השימוש ביישום ושיחה עם ה- AI במהלך הראיונות."
    },
    "notifications": {
      "saved": "הגדרות נשמרו"
    },
    "search": {
      "not_found": "לא נמצאו תוצאות."
    }
  },
  "interview": {
    "button": {
      "new": "ראיון חדש",
      "resume": "ראיון לחדש"
    },
    "generating": "יצירת ראיון חדש"
  },
  "chat": {
    "error": {
      "label": {
        "tap_to_retry": "הקש כדי לנסות שוב"
      }
    }
  },
  "text_input": {
    "placeholder": "הקלד את ההודעה שלך ...",
    "max_length": "אורך מקסימום הגיע"
  },
  "cooldown": {
    "description": "הגרסה החינמית של האפליקציה מאפשרת לך לצאת לראיון אחד לשעה.\n\nאם תרצה להסיר את המגבלות, הסר את המודעות וקבל דוח משוב עם עצות כיצד להשתפר לאחר כל ראיון, שקול להירשם לפרמיה.",
    "active": "המתן לטיימר COOLDOWN לפני שתפיק ראיון חדש.\n\nאם ברצונך להסיר את Cooldowns, הסר מודעות וקבל דוח משוב עם עצות כיצד להשתפר לאחר כל ראיון, שקול להירשם לפרמיה.",
    "timer": {
      "wait": "לַחֲכוֹת",
      "second": "שְׁנִיָה",
      "seconds": "שניות"
    }
  },
  "report": {
    "title": "דִוּוּחַ",
    "summary": "תַקצִיר",
    "feedback": "מָשׁוֹב",
    "advice": "עֵצָה",
    "button": {
      "view": "צפה בדוח",
      "unlock": "ביטול הנעילה",
      "get": "קבל דוח"
    },
    "generating": "ייצור דוח ..."
  },
  "review": {
    "request": "אם אהבת את האפליקציה, אנא שקול להשאיר ביקורת כדי לעזור לנו.\n\n⭐⭐⭐⭐⭐",
    "thanks": "תודה רבה!"
  },
  "notification": {
    "new_interview": {
      "title": "ראיון חדש זמין!",
      "message": "יש לך ראיון חדש זמין לקחת על עצמו את Job Intelliviewer."
    }
  },
  "iap": {
    "subscription": {
      "title": "פּרֶמיָה",
      "type": "מִנוּי",
      "subscribe": "הירשם",
      "invitation": "הירשם לפרמיום",
      "active": "מנוי פרימיום פעיל",
      "thanks": "תודה על המנוי לפרמיום! אנו מאחלים לך מזל טוב והצלחה בכל הראיונות העתידיים שלך!",
      "menu": {
        "title": "מנוי פרימיום",
        "subtitle": "הירשם לתוכנית הפרימיום"
      }
    },
    "error": {
      "subscription": "שגיאה בניסיון לאמת את הרכישה שלך.",
      "connection": "שגיאת חיבור.\n\nלא ניתן להתחבר לחנות.",
      "products": "לא ניתן לבדוק אפשרויות מוצר.",
      "subscription_options": "לא ניתן לטעון תוכניות מנוי.\n\nאנא, בדוק את חיבור האינטרנט שלך, או נסה שוב מאוחר יותר."
    }
  },
  "error": {
    "title": "שְׁגִיאָה",
    "unexpected": "משהו השתבש ... אתה לא אמור לראות את זה! 😱",
    "connection": "קֶשֶׁר",
    "connection_fix": "בדוק את חיבור האינטרנט שלך ונסה שוב מאוחר יותר.",
    "ai": {
      "no_response": "אין תגובה",
      "unexpected": "לֹא צָפוּי",
      "internal_server_error": "שגיאת שרת פנימית"
    }
  },
  "release": {
    "store": {
      "short_description": "תרגול לראיון העבודה הבא שלך עם סימולטור AI מציאותי זה",
      "full_description": "האם נטילת ראיונות עבודה גורמים לך לחיצה וחרדה?\nאולי אתה עדיין מרגיש לא מוכן לקחת ראיונות עבודה?\nזו האפליקציה המושלמת לתרגל את כישורי השיחה שלך במסגרת ראיון עבודה!\n\nIntelliviewer Job משתמש בכוח של בינה מלאכותית כדי לערוך ראיונות עבודה מדומים ריאליסטיים כדי לעזור לך לרתום את כישורי השיחה הדרושים בכדי לעשות רושם טוב על מגייסי החיים האמיתיים ולהפוך אותך למוכן לאס את הראיון הבא שלך.\n\nהראיונות מותאמים לתפקיד העבודה שאתה מחפש, ויהיה מעוצב ומותאם עם שאלות הקשורות למטרות שלך כדי לייצג טוב יותר ראיון עבודה אמיתי.\n\nמשתמשי פרימיום יקבלו גם דוח בסוף כל ראיון המסכם את השיחה עם משוב ועצות כיצד לשפר את הסיכוי שלך להתקבל לעבודה בראיון עבודה אמיתי.",
      "taglines": [
        "היו מוכנים לתפקיד הבא שלכם!",
        "תרגול לראיון העבודה הבא שלך!",
        "אייס ראיון העבודה הבא שלך עם AI!",
        "ההצלחה המקצועית הבאה שלך מחכה לך כאן!"
      ],
      "premium_benefits": [
        "מסיר מודעות",
        "ראיונות בלתי מוגבלים",
        "קבל דוחות עם משוב וייעוץ"
      ]
    },
    "revenue_cat": {
      "premium": "פּרֶמיָה",
      "monthly": "יַרחוֹן",
      "annual": "שְׁנָתִי",
      "cancel_anytime": "בטל בכל עת",
      "save_discount": "לְהַצִיל",
      "subscribe": "הירשם",
      "restore_purchases": "שחזור רכישות",
      "premium_benefits": [
        "הסר מודעות",
        "ראיונות בלתי מוגבלים ללא קולים",
        "קבל דוחות עם משוב וייעוץ לאחר ראיונות"
      ]
    }
  },
  "translation": {
    "title": "עזור לתרגם",
    "description": "עזרו בתרגום יישום זה לשפות אחרות."
  }
}